rtl/generated/control_shared.sv
// Generated by tools/generate.py. Edit spec/instructions.csv instead.
module control_shared #(parameter bit ENABLE_M = 0)
  (input logic [31:0] insn, output decode_pkg::ctrl_t ctrl);
  import decode_pkg::*;
  logic [98:0] product;
  assign product[0] = 1'b1 && ((insn & 32'h0000707f) == 32'h0000000f);
  assign product[1] = 1'b1 && ((insn & 32'hffefffff) == 32'h00000073);
  assign product[2] = 1'b1 && ((insn & 32'hffffffff) == 32'h00000073);
  assign product[3] = 1'b1 && ((insn & 32'hffffffff) == 32'h00100073);
  assign product[4] = 1'b1 && ((insn & 32'h0000607f) == 32'h00004003);
  assign product[5] = 1'b1 && ((insn & 32'h0000307f) == 32'h00001003);
  assign product[6] = 1'b1 && ((insn & 32'h0000705f) == 32'h00001003);
  assign product[7] = 1'b1 && ((insn & 32'h0000705f) == 32'h00002003);
  assign product[8] = 1'b1 && ((insn & 32'h0000005f) == 32'h00000017);
  assign product[9] = 1'b1 && ((insn & 32'h0000007f) == 32'h0000006f);
  assign product[10] = 1'b1 && ((insn & 32'h0000107f) == 32'h00000013);
  assign product[11] = 1'b1 && ((insn & 32'h0000207f) == 32'h00000003);
  assign product[12] = 1'b1 && ((insn & 32'h0000207f) == 32'h00002013);
  assign product[13] = 1'b1 && ((insn & 32'h0000306f) == 32'h00000003);
  assign product[14] = 1'b1 && ((insn & 32'h0000506f) == 32'h00000003);
  assign product[15] = 1'b1 && ((insn & 32'h0000707f) == 32'h00000067);
  assign product[16] = 1'b1 && ((insn & 32'hbe00705f) == 32'h00005013);
  assign product[17] = 1'b1 && ((insn & 32'hbe00707f) == 32'h00000033);
  assign product[18] = 1'b1 && ((insn & 32'hfe00007f) == 32'h00000033);
  assign product[19] = 1'b1 && ((insn & 32'hfe00305f) == 32'h00001013);
  assign product[20] = ENABLE_M && ((insn & 32'hfe00007f) == 32'h02000033);
  assign product[21] = 1'b1 && ((insn & 32'h0000207f) == 32'h00000063);
  assign product[22] = 1'b1 && ((insn & 32'h0000407f) == 32'h00004063);
  assign product[23] = 1'b1 && ((insn & 32'h0000507f) == 32'h00000023);
  assign product[24] = 1'b1 && ((insn & 32'h0000603f) == 32'h00000023);
  assign product[25] = 1'b1 && ((insn & 32'hbe00707f) == 32'h00005033);
  assign product[26] = 1'b1 && ((insn & 32'h0000505f) == 32'h00000003);
  assign product[27] = 1'b1 && ((insn & 32'h0000605f) == 32'h00000003);
  assign product[28] = 1'b1 && ((insn & 32'h0000707b) == 32'h00000063);
  assign product[29] = 1'b1 && ((insn & 32'h0000007f) == 32'h00000017);
  assign product[30] = 1'b1 && ((insn & 32'h0000703f) == 32'h00000023);
  assign product[31] = 1'b1 && ((insn & 32'h0000706f) == 32'h00000003);
  assign product[32] = 1'b1 && ((insn & 32'h0000707f) == 32'h00003013);
  assign product[33] = 1'b1 && ((insn & 32'h0000707f) == 32'h00005063);
  assign product[34] = 1'b1 && ((insn & 32'h0000707f) == 32'h00006013);
  assign product[35] = 1'b1 && ((insn & 32'h0000707f) == 32'h00006063);
  assign product[36] = 1'b1 && ((insn & 32'hfe00507f) == 32'h00001033);
  assign product[37] = 1'b1 && ((insn & 32'hfe00607f) == 32'h00000033);
  assign product[38] = 1'b1 && ((insn & 32'hfe00707f) == 32'h00006033);
  assign product[39] = ENABLE_M && ((insn & 32'hfe00107f) == 32'h02000033);
  assign product[40] = 1'b1 && ((insn & 32'h0000707f) == 32'h00000063);
  assign product[41] = 1'b1 && ((insn & 32'h0000707f) == 32'h00004013);
  assign product[42] = 1'b1 && ((insn & 32'h0000707f) == 32'h00007013);
  assign product[43] = 1'b1 && ((insn & 32'h0000707f) == 32'h00007063);
  assign product[44] = 1'b1 && ((insn & 32'hfe00507f) == 32'h00005033);
  assign product[45] = 1'b1 && ((insn & 32'hfe00607f) == 32'h00004033);
  assign product[46] = 1'b1 && ((insn & 32'hfe00707f) == 32'h40000033);
  assign product[47] = ENABLE_M && ((insn & 32'hfe00307f) == 32'h02000033);
  assign product[48] = ENABLE_M && ((insn & 32'hfe00307f) == 32'h02003033);
  assign product[49] = 1'b1 && ((insn & 32'h0000307f) == 32'h00001063);
  assign product[50] = 1'b1 && ((insn & 32'h0000607f) == 32'h00002013);
  assign product[51] = 1'b1 && ((insn & 32'hfe00607f) == 32'h00002033);
  assign product[52] = 1'b1 && ((insn & 32'hfe00705f) == 32'h00005013);
  assign product[53] = ENABLE_M && ((insn & 32'hfe00507f) == 32'h02005033);
  assign product[54] = ENABLE_M && ((insn & 32'hfe00607f) == 32'h02006033);
  assign product[55] = ENABLE_M && ((insn & 32'hfe00707f) == 32'h02000033);
  assign product[56] = 1'b1 && ((insn & 32'h0000507f) == 32'h00005063);
  assign product[57] = 1'b1 && ((insn & 32'h0000607f) == 32'h00000063);
  assign product[58] = 1'b1 && ((insn & 32'h0000607f) == 32'h00006013);
  assign product[59] = 1'b1 && ((insn & 32'hfe00607f) == 32'h00006033);
  assign product[60] = 1'b1 && ((insn & 32'hfe00705f) == 32'h40005013);
  assign product[61] = ENABLE_M && ((insn & 32'hfe00107f) == 32'h02001033);
  assign product[62] = ENABLE_M && ((insn & 32'hfe00207f) == 32'h02002033);
  assign product[63] = ENABLE_M && ((insn & 32'hfe00407f) == 32'h02004033);
  assign product[64] = 1'b1 && ((insn & 32'h0000607f) == 32'h00000023);
  assign product[65] = 1'b1 && ((insn & 32'hbe00707f) == 32'h00005013);
  assign product[66] = 1'b1 && ((insn & 32'hfe00307f) == 32'h00001013);
  assign product[67] = 1'b1 && ((insn & 32'h0000007f) == 32'h00000037);
  assign product[68] = 1'b1 && ((insn & 32'h0000307f) == 32'h00000063);
  assign product[69] = 1'b1 && ((insn & 32'h0000507f) == 32'h00000003);
  assign product[70] = 1'b1 && ((insn & 32'h0000507f) == 32'h00004063);
  assign product[71] = 1'b1 && ((insn & 32'h0000707f) == 32'h00001023);
  assign product[72] = 1'b1 && ((insn & 32'h0000707f) == 32'h00005003);
  assign product[73] = 1'b1 && ((insn & 32'hfe00707f) == 32'h00001013);
  assign product[74] = 1'b1 && ((insn & 32'hfe00707f) == 32'h00002033);
  assign product[75] = 1'b1 && ((insn & 32'hfe00707f) == 32'h00004033);
  assign product[76] = 1'b1 && ((insn & 32'hfe00707f) == 32'h00007033);
  assign product[77] = 1'b1 && ((insn & 32'h0000507f) == 32'h00004013);
  assign product[78] = 1'b1 && ((insn & 32'h0000707f) == 32'h00001063);
  assign product[79] = 1'b1 && ((insn & 32'h0000707f) == 32'h00002023);
  assign product[80] = 1'b1 && ((insn & 32'h0000707f) == 32'h00004063);
  assign product[81] = 1'b1 && ((insn & 32'hfe00307f) == 32'h00001033);
  assign product[82] = ENABLE_M && ((insn & 32'hfe00307f) == 32'h02001033);
  assign product[83] = ENABLE_M && ((insn & 32'hfe00307f) == 32'h02002033);
  assign product[84] = 1'b1 && ((insn & 32'h0000307f) == 32'h00002013);
  assign product[85] = 1'b1 && ((insn & 32'h0000706f) == 32'h00002003);
  assign product[86] = 1'b1 && ((insn & 32'h0000706f) == 32'h00004003);
  assign product[87] = 1'b1 && ((insn & 32'hfe00307f) == 32'h00002033);
  assign product[88] = 1'b1 && ((insn & 32'hfe00507f) == 32'h00000033);
  assign product[89] = ENABLE_M && ((insn & 32'hfe00507f) == 32'h02004033);
  assign product[90] = ENABLE_M && ((insn & 32'hfe00607f) == 32'h02004033);
  assign product[91] = ENABLE_M && ((insn & 32'hfe00707f) == 32'h02003033);
  assign product[92] = 1'b1 && ((insn & 32'h0000607f) == 32'h00006063);
  assign product[93] = 1'b1 && ((insn & 32'hfe00705f) == 32'h00001013);
  assign product[94] = ENABLE_M && ((insn & 32'hfe00207f) == 32'h02000033);
  assign product[95] = ENABLE_M && ((insn & 32'hfe00407f) == 32'h02000033);
  assign product[96] = ENABLE_M && ((insn & 32'hfe00707f) == 32'h02007033);
  assign product[97] = 1'b1 && ((insn & 32'hfe00307f) == 32'h00003033);
  assign product[98] = 1'b1 && ((insn & 32'hfe00407f) == 32'h00004033);
  assign ctrl[0] = product[0] | product[1];
  assign ctrl[1] = product[2];
  assign ctrl[2] = product[3];
  assign ctrl[3] = product[4];
  assign ctrl[4] = product[5] | product[6];
  assign ctrl[5] = product[7];
  assign ctrl[6] = product[8] | product[9] | product[10] | product[11] | product[12] | product[13] | product[14] | product[15] | product[16] | product[17] | product[18] | product[19] | product[20];
  assign ctrl[7] = product[21] | product[22] | product[23] | product[24] | product[17] | product[25] | product[18] | product[20];
  assign ctrl[8] = product[10] | product[11] | product[21] | product[12] | product[13] | product[22] | product[26] | product[14] | product[24] | product[27] | product[28] | product[16] | product[17] | product[18] | product[19] | product[20];
  assign ctrl[9] = product[29] | product[9] | product[11] | product[26] | product[27] | product[30] | product[31] | product[28] | product[32] | product[33] | product[34] | product[35] | product[19] | product[36] | product[37] | product[38] | product[39];
  assign ctrl[10] = product[40] | product[41] | product[42] | product[43] | product[19] | product[44] | product[45] | product[46] | product[47] | product[48];
  assign ctrl[11] = product[49] | product[22] | product[50] | product[41] | product[51] | product[45] | product[52] | product[53] | product[54] | product[55];
  assign ctrl[12] = product[49] | product[56] | product[57] | product[58] | product[59] | product[60] | product[55];
  assign ctrl[13] = product[61] | product[62] | product[63];
  assign ctrl[14] = product[8] | product[9] | product[10] | product[12] | product[23] | product[64] | product[15] | product[16] | product[17] | product[18] | product[19] | product[1];
  assign ctrl[15] = product[11] | product[26] | product[27] | product[0] | product[1];
  assign ctrl[16] = product[9] | product[21] | product[22] | product[28] | product[0] | product[1];
  assign ctrl[17] = product[20];
  assign ctrl[18] = product[8] | product[23] | product[64] | product[16] | product[17] | product[18] | product[19] | product[20];
  assign ctrl[19] = product[9] | product[10] | product[11] | product[12] | product[13] | product[26] | product[14] | product[27] | product[15] | product[65] | product[66];
  assign ctrl[20] = product[8] | product[9] | product[21] | product[22] | product[65] | product[66];
  assign ctrl[21] = product[67] | product[9] | product[68] | product[69] | product[70] | product[31] | product[71] | product[32] | product[72] | product[34] | product[60] | product[73] | product[74] | product[75] | product[76] | product[46] | product[2] | product[39];
  assign ctrl[22] = product[29] | product[9] | product[13] | product[77] | product[4] | product[0] | product[78] | product[79] | product[80] | product[43] | product[16] | product[81] | product[74] | product[2] | product[82] | product[83];
  assign ctrl[23] = product[68] | product[5] | product[84] | product[77] | product[57] | product[50] | product[4] | product[85] | product[86] | product[28] | product[0] | product[17] | product[87] | product[88] | product[37] | product[59] | product[2] | product[89] | product[90] | product[91];
  assign ctrl[24] = product[11] | product[69] | product[56] | product[92] | product[42] | product[17] | product[65] | product[66] | product[88] | product[37] | product[93] | product[3] | product[39] | product[94] | product[95];
  assign ctrl[25] = product[10] | product[12] | product[23] | product[64] | product[17] | product[65] | product[66] | product[88] | product[37] | product[93] | product[96];
  assign ctrl[26] = product[0] | product[25] | product[97] | product[98] | product[1] | product[20];
  assign ctrl[27] = product[8] | product[9] | product[10] | product[11] | product[21] | product[12] | product[13] | product[22] | product[26] | product[14] | product[24] | product[27] | product[28] | product[0] | product[16] | product[17] | product[18] | product[19] | product[1] | product[20];
endmodule

rtl/superscalar_decoder.sv
// Combinational, independently valid decode lanes. Lane 0 is oldest.
module superscalar_decoder #(
  parameter int WIDTH = 4,
  parameter int IMPL = 2, // 0: direct case, 1: exact PLA, 2: shared PLA
  parameter bit ENABLE_M = 0
) (
  input logic [WIDTH*32-1:0] instructions,
  input logic [WIDTH-1:0] lane_valid,
  output logic [WIDTH*decode_pkg::DECODE_W-1:0] decoded,
  output logic [WIDTH*WIDTH-1:0] raw_rs1, raw_rs2, waw
);
  import decode_pkg::*;
  decode_t lanes [WIDTH];
  for (genvar i = 0; i < WIDTH; i++) begin : lane
    ctrl_t ctrl;
    if (IMPL == 0) begin : direct
      control_direct #(.ENABLE_M(ENABLE_M)) u (instructions[i*32+:32], ctrl);
    end else if (IMPL == 1) begin : pla
      control_pla #(.ENABLE_M(ENABLE_M)) u (instructions[i*32+:32], ctrl);
    end else begin : shared
      control_shared #(.ENABLE_M(ENABLE_M)) u (instructions[i*32+:32], ctrl);
    end
    always_comb lanes[i] = payload(instructions[i*32+:32], lane_valid[i], ctrl);
    assign decoded[i*DECODE_W+:DECODE_W] = lanes[i];
  end
  // Bit younger*WIDTH+older records every in-bundle dependency.
  // A future rename/forwarding stage must select the youngest matching writer.
  always_comb begin
    raw_rs1 = '0; raw_rs2 = '0; waw = '0;
    for (int younger = 0; younger < WIDTH; younger++) begin
      for (int older = 0; older < younger; older++) begin
        if (lanes[younger].valid && !lanes[younger].illegal &&
            lanes[older].valid && !lanes[older].illegal &&
            lanes[older].ctrl.writes_rd) begin
          raw_rs1[younger*WIDTH+older] = lanes[younger].ctrl.uses_rs1 &&
            lanes[younger].rs1 == lanes[older].rd;
          raw_rs2[younger*WIDTH+older] = lanes[younger].ctrl.uses_rs2 &&
            lanes[younger].rs2 == lanes[older].rd;
          waw[younger*WIDTH+older] = lanes[younger].ctrl.writes_rd &&
            lanes[younger].rd == lanes[older].rd;
        end
      end
    end
  end
endmodule

tb/tb_pipeline.sv
`timescale 1ns/1ps
module tb_pipeline;
  import decode_pkg::*;
  logic clk=0;
  always #5 clk=~clk;
  logic reset,flush,in_valid,in_ready,out_valid,out_ready;
  logic [127:0] instructions;
  logic [3:0] lane_valid;
  wire [4*DECODE_W-1:0] result,comb;
  wire [15:0] r1,r2,ww,c1,c2,cw;
  logic expected_valid=0;
  logic [4*DECODE_W-1:0] expected_data='0;
  logic [15:0] expected_r1=0,expected_r2=0,expected_waw=0;
  logic [31:0] rng=32'h1234abcd;
  integer accepted=0,stalls=0,flushes=0,summary;
  function automatic logic [31:0] random_word();
    rng=rng^(rng<<13);rng=rng^(rng>>17);rng=rng^(rng<<5);
    return rng;
  endfunction
  decode_pipeline #(.ENABLE_M(1)) dut
    (clk,reset,flush,in_valid,in_ready,instructions,lane_valid,out_valid,out_ready,result,r1,r2,ww);
  superscalar_decoder #(.ENABLE_M(1)) reference_comb
    (instructions,lane_valid,comb,c1,c2,cw);
  initial begin
    reset=1;flush=0;in_valid=0;out_ready=0;instructions=0;lane_valid=0;
    @(posedge clk); #1;
    if(out_valid!==0 || result!==0) $fatal(1,"Reset failed");
    for(int cycle=0;cycle<4000;cycle++) begin
      @(negedge clk);
      reset=(cycle%257==0);flush=(cycle%71==0);
      in_valid=(random_word()%5!=0);out_ready=(random_word()%3!=0);
      lane_valid=random_word();
      for(int lane=0;lane<4;lane++) instructions[lane*32+:32]=random_word();
      #1;
      if(in_ready !== (!reset && !flush && (!expected_valid || out_ready)))
        $fatal(1,"Ready mismatch cycle %0d",cycle);
      if(reset || flush) begin
        expected_valid=0;expected_data=0;expected_r1=0;expected_r2=0;expected_waw=0;
        if(flush) flushes++;
      end else if(in_ready) begin
        expected_valid=in_valid;
        expected_data=in_valid?comb:'0;
        expected_r1=in_valid?c1:'0;expected_r2=in_valid?c2:'0;expected_waw=in_valid?cw:'0;
        if(in_valid) accepted++;
      end else stalls++;
      @(posedge clk);#1;
      if(out_valid!==expected_valid || result!==expected_data || r1!==expected_r1 || r2!==expected_r2 || ww!==expected_waw)
        $fatal(1,"Pipeline scoreboard mismatch cycle %0d",cycle);
    end
    if(accepted<100 || stalls<100 || flushes<10) $fatal(1,"Insufficient handshake coverage");
    summary=$fopen("../pipeline_simulation.json","w");
    $fdisplay(summary,"{\"status\":\"PASS\",\"cycles\":4000,\"accepted\":%0d,\"stalls\":%0d,\"flushes\":%0d}",accepted,stalls,flushes);
    $fclose(summary);
    $display("PASS: pipeline 4000 cycles, %0d accepted, %0d stalled, %0d flushes",accepted,stalls,flushes);
    $finish;
  end
endmodule

reports/evidence/pipeline_waveform.vcd
$date
   Fri Oct  9 00:02:36 2026
$end

$version
  2026.1
$end

$timescale
  1ps
$end

$scope module tb_pipeline $end
$var reg 1 ! clk $end
$var reg 1 " reset $end
$var reg 1 # flush $end
$var reg 1 $ in_valid $end
$var reg 1 % in_ready $end
$var reg 1 & out_valid $end
$var reg 1 ' out_ready $end
$upscope $end
$enddefinitions $end

#0
$dumpvars
0!
1"
0#
0$
0%
x&
0'
$end

#5000
1!
0&

#10000
0!
1#
1$

#15000
1!

#20000
0!
0"
0#
1%

#25000
1!
0%
1&

#30000
0!
1%
1'

#35000
1!

#40000
0!

#45000
1!

#50000
0!
0$

#55000
1!
0&

#60000
0!
1$

#65000
1!
1&

#70000
0!
0%
0'

#75000
1!

#80000
0!
0$
1%
1'

#85000
1!
0&

#90000
0!

#95000
1!

#100000
0!

#105000
1!

#110000
0!
0'

#115000
1!

#120000
0!
1$
1'

#125000
1!
1&

#130000
0!
0$

#135000
1!
0&

#140000
0!
1$

#145000
1!
1&

#150000
0!
0%
0'

#155000
1!

#160000
0!

#165000
1!

#170000
0!
0$
1%
1'

#175000
1!
0&

#180000
0!

#185000
1!

#190000
0!
1$

#195000
1!
1&

#200000
0!

#205000
1!

#210000
0!

#215000
1!

#220000
0!

#225000
1!

#230000
0!
0%
0'

#235000
1!

#240000
0!

#245000
1!

#250000
0!
0$

#255000
1!

#260000
0!
1$
1%
1'

#265000
1!

#270000
0!

#275000
1!

#280000
0!

#285000
1!

#290000
0!

#295000
1!

#300000
0!
0%
0'

#305000
1!

#310000
0!
1%
1'

#315000
1!

#320000
0!

#325000
1!

#330000
0!
0%
0'

#335000
1!

#340000
0!

#345000
1!

#350000
0!

#355000
1!

#360000
0!
0$
1%
1'

#365000
1!
0&

#370000
0!

#375000
1!

#380000
0!
1$

#385000
1!
1&

#390000
0!
0%
0'

#395000
1!

#400000
0!
1%
1'

#405000
1!

#410000
0!

#415000
1!

#420000
0!

#425000
1!

#430000
0!

#435000
1!

#440000
0!
0$

#445000
1!
0&

#450000
0!
0'

#455000
1!

#460000
0!
1'

#465000
1!

#470000
0!
1$

#475000
1!
1&

#480000
0!
0$

#485000
1!
0&

#490000
0!
1$

#495000
1!
1&

#500000
0!
0%
0'

#505000
1!

#510000
0!
1%
1'

#515000
1!

#520000
0!

#525000
1!

#530000
0!

#535000
1!

#540000
0!
0%
0'

#545000
1!

#550000
0!
1%
1'

#555000
1!

#560000
0!
0$

#565000
1!
0&

#570000
0!

#575000
1!

#580000
0!
1$
0'

#585000
1!
0%
1&

#590000
0!
0$

#595000
1!

#600000
0!
1$
1%
1'

#605000
1!

#610000
0!

#615000
1!

#620000
0!

#625000
1!

#630000
0!

#635000
1!

#640000
0!

#645000
1!

#650000
0!

#655000
1!

#660000
0!
0$

#665000
1!
0&

#670000
0!
0'

#675000
1!

#680000
0!
1$
1'

#685000
1!
1&

#690000
0!
0$

#695000
1!
0&

#700000
0!
1$

#705000
1!
1&

#710000
0!

#715000
1!

#720000
0!
1#
0%

#725000
1!
0&

#730000
0!
0#
1%

#735000
1!
1&

#740000
0!

#745000
1!

#750000
0!
0$
0%
0'

#755000
1!

#760000
0!
1$
1%
1'

#765000
1!

#770000
0!

#775000
1!

#780000
0!

#785000
1!

#790000
0!
0%
0'

#795000
1!

#800000
0!
1%
1'

#805000
1!

#810000
0!
0%
0'

#815000
1!

#820000
0!
1%
1'

#825000
1!

#830000
0!

#835000
1!

#840000
0!
0$

#845000
1!
0&

#850000
0!
1$

#855000
1!
1&

#860000
0!

#865000
1!

#870000
0!
0$
0%
0'

#875000
1!

#880000
0!
1$

#885000
1!

#890000
0!
1%
1'

#895000
1!

#900000
0!

#905000
1!

#910000
0!
0%
0'

#915000
1!

#920000
0!
1%
1'

#925000
1!

#930000
0!

#935000
1!

#940000
0!

#945000
1!

#950000
0!
0%
0'

#955000
1!

#960000
0!

#965000
1!

#970000
0!
0$

#975000
1!

#980000
0!
1$

#985000
1!

#990000
0!
1%
1'

#995000
1!

#1000000
0!
0%
0'

#1005000
1!

#1010000
0!
1%
1'

#1015000
1!

#1020000
0!

#1025000
1!

#1030000
0!

#1035000
1!

#1040000
0!

#1045000
1!

#1050000
0!
0%
0'

#1055000
1!

#1060000
0!
1%
1'

#1065000
1!

#1070000
0!
0%
0'

#1075000
1!

#1080000
0!
1%
1'

#1085000
1!

#1090000
0!

#1095000
1!

#1100000
0!

#1105000
1!

#1110000
0!
0$

#1115000
1!
0&

#1120000
0!
1$

#1125000
1!
1&

#1130000
0!

#1135000
1!

#1140000
0!

#1145000
1!

#1150000
0!

#1155000
1!

#1160000
0!

#1165000
1!

#1170000
0!

#1175000
1!

#1180000
0!

#1185000
1!

#1190000
0!
0$
0%
0'

#1195000
1!

#1200000
0!
1$

#1205000
1!

#1210000
0!
1%
1'

#1215000
1!

#1220000
0!

#1225000
1!

#1230000
0!
0$

#1235000
1!
0&

#1240000
0!
1$

#1245000
1!
1&

#1250000
0!

#1255000
1!

#1260000
0!
0$
0%
0'

#1265000
1!

#1270000
0!
1$

#1275000
1!

#1280000
0!
1%
1'

#1285000
1!

#1290000
0!

#1295000
1!

#1300000
0!

#1305000
1!

#1310000
0!

#1315000
1!

#1320000
0!
0$

#1325000
1!
0&

#1330000
0!
1$

#1335000
1!
1&

#1340000
0!

#1345000
1!

#1350000
0!
0%
0'

#1355000
1!

#1360000
0!
1%
1'

#1365000
1!

#1370000
0!

#1375000
1!

#1380000
0!

#1385000
1!

#1390000
0!

#1395000
1!

#1400000
0!

#1405000
1!

#1410000
0!

#1415000
1!

#1420000
0!

#1425000
1!

#1430000
0!
1#
0%

#1435000
1!
0&

#1440000
0!
0#
1%
0'

#1445000
1!
0%
1&

#1450000
0!

#1455000
1!

#1460000
0!
1%
1'

#1465000
1!

#1470000
0!
0$

#1475000
1!
0&

#1480000
0!
1$

#1485000
1!
1&

#1490000
0!

#1495000
1!

#1500000
0!
0%
0'

#1505000
1!

#1510000
0!

#1515000
1!

#1520000
0!

#1525000
1!

#1530000
0!
1%
1'

#1535000
1!

#1540000
0!
0$

#1545000
1!
0&

#1550000
0!
1$

#1555000
1!
1&

#1560000
0!
0$

#1565000
1!
0&

#1570000
0!
1$
0'

#1575000
1!
0%
1&

#1580000
0!
1%
1'

#1585000
1!

#1590000
0!
0%
0'

#1595000
1!

#1600000
0!

#1605000
1!

#1610000
0!

#1615000
1!

#1620000
0!
1%
1'

#1625000
1!

#1630000
0!

#1635000
1!

#1640000
0!
0$

#1645000
1!
0&

#1650000
0!

#1655000
1!

#1660000
0!
1$

#1665000
1!
1&

#1670000
0!
0%
0'

#1675000
1!

#1680000
0!
1%
1'

#1685000
1!

#1690000
0!

#1695000
1!

#1700000
0!
0$

#1705000
1!
0&

#1710000
0!
1$
0'

#1715000
1!
0%
1&

#1720000
0!

#1725000
1!

#1730000
0!
1%
1'

#1735000
1!

#1740000
0!

#1745000
1!

#1750000
0!
0%
0'

#1755000
1!

#1760000
0!

#1765000
1!

#1770000
0!
1%
1'

#1775000
1!

#1780000
0!

#1785000
1!

#1790000
0!
0$

#1795000
1!
0&

#1800000
0!
1$
0'

#1805000
1!
0%
1&

#1810000
0!
1%
1'

#1815000
1!

#1820000
0!

#1825000
1!

#1830000
0!

#1835000
1!

#1840000
0!

#1845000
1!

#1850000
0!
0$

#1855000
1!
0&

#1860000
0!
1$

#1865000
1!
1&

#1870000
0!
0%
0'

#1875000
1!

#1880000
0!

#1885000
1!

#1890000
0!
1%
1'

#1895000
1!

#1900000
0!

#1905000
1!

#1910000
0!
0%
0'

#1915000
1!

#1920000
0!
1%
1'

#1925000
1!

#1930000
0!
0$

#1935000
1!
0&

#1940000
0!
1$

#1945000
1!
1&

#1950000
0!
0%
0'

#1955000
1!

#1960000
0!
1%
1'

#1965000
1!

#1970000
0!

#1975000
1!

#1980000
0!
0%
0'

#1985000
1!

#1990000
0!

#1995000
1!

#2000000
0!
0$
1%
1'

#2005000
1!
0&

#2010000
0!
1$

#2015000
1!
1&

#2020000
0!
0%
0'

#2025000
1!

#2030000
0!
1%
1'

#2035000
1!

#2040000
0!

#2045000
1!

#2050000
0!
0%
0'

#2055000
1!

#2060000
0!
1%
1'

#2065000
1!

#2070000
0!

#2075000
1!

#2080000
0!

#2085000
1!

#2090000
0!

#2095000
1!

#2100000
0!
0%
0'

#2105000
1!

#2110000
0!
1%
1'

#2115000
1!

#2120000
0!
0%
0'

#2125000
1!

#2130000
0!

#2135000
1!

#2140000
0!
1#
1'

#2145000
1!
0&

#2150000
0!
0#
1%
0'

#2155000
1!
0%
1&

#2160000
0!
1%
1'

#2165000
1!

#2170000
0!

#2175000
1!

#2180000
0!

#2185000
1!

#2190000
0!
0$

#2195000
1!
0&

#2200000
0!
1$

#2205000
1!
1&

#2210000
0!
0%
0'

#2215000
1!

#2220000
0!
1%
1'

#2225000
1!

#2230000
0!

#2235000
1!

#2240000
0!

#2245000
1!

#2250000
0!

#2255000
1!

#2260000
0!
0$
0%
0'

#2265000
1!

#2270000
0!
1$

#2275000
1!

#2280000
0!
1%
1'

#2285000
1!

#2290000
0!
0%
0'

#2295000
1!

#2300000
0!

#2305000
1!

#2310000
0!
0$
1%
1'

#2315000
1!
0&

#2320000
0!
1$

#2325000
1!
1&

#2330000
0!
0%
0'

#2335000
1!

#2340000
0!
1%
1'

#2345000
1!

#2350000
0!
0%
0'

#2355000
1!

#2360000
0!
1%
1'

#2365000
1!

#2370000
0!

#2375000
1!

#2380000
0!
0$

#2385000
1!
0&

#2390000
0!
1$

#2395000
1!
1&

#2400000
0!

#2405000
1!

#2410000
0!

#2415000
1!

#2420000
0!

#2425000
1!

#2430000
0!
0%
0'

#2435000
1!

#2440000
0!

#2445000
1!

#2450000
0!

#2455000
1!

#2460000
0!
0$
1%
1'

#2465000
1!
0&

#2470000
0!
1$
0'

#2475000
1!
0%
1&

#2480000
0!
0$

#2485000
1!

#2490000
0!
1$

#2495000
1!

#2500000
0!
1%
1'

#2505000
1!

#2510000
0!
0$

#2515000
1!
0&

#2520000
0!
0'

#2525000
1!

#2530000
0!
1$
1'

#2535000
1!
1&

#2540000
0!
0%
0'

#2545000
1!

#2550000
0!
1%
1'

#2555000
1!

#2560000
0!
0%
0'

#2565000
1!

#2570000
0!
1%
1'

#2575000
1!

#2580000
0!
1"
0%
0'

#2585000
1!
0&

#2590000
0!
0"
1%
1'

#2595000
1!
1&

#2600000
0!

#2605000
1!

#2610000
0!

#2615000
1!

#2620000
0!

#2625000
1!

#2630000
0!

#2635000
1!

#2640000
0!
0%
0'

#2645000
1!

#2650000
0!
1%
1'

#2655000
1!

#2660000
0!

#2665000
1!

#2670000
0!

#2675000
1!

#2680000
0!

#2685000
1!

#2690000
0!

#2695000
1!

#2700000
0!

#2705000
1!

#2710000
0!
0%
0'

#2715000
1!

#2720000
0!
1%
1'

#2725000
1!

#2730000
0!
0$

#2735000
1!
0&

#2740000
0!
1$

#2745000
1!
1&

#2750000
0!

#2755000
1!

#2760000
0!
0%
0'

#2765000
1!

#2770000
0!

#2775000
1!

#2780000
0!
1%
1'

#2785000
1!

#2790000
0!

#2795000
1!

#2800000
0!

#2805000
1!

#2810000
0!

#2815000
1!

#2820000
0!

#2825000
1!

#2830000
0!

#2835000
1!

#2840000
0!
0$

#2845000
1!
0&

#2850000
0!
1#
1$
0%
0'

#2855000
1!

#2860000
0!
0#
0$
1%

#2865000
1!

#2870000
0!

#2875000
1!

#2880000
0!
1$
1'

#2885000
1!
1&

#2890000
0!
0%
0'

#2895000
1!

#2900000
0!
0$
1%
1'

#2905000
1!
0&

#2910000
0!
1$

#2915000
1!
1&

#2920000
0!

#2925000
1!

#2930000
0!

#2935000
1!

#2940000
0!
0%
0'

#2945000
1!

#2950000
0!
1%
1'

#2955000
1!

#2960000
0!
0%
0'

#2965000
1!

#2970000
0!
1%
1'

#2975000
1!

#2980000
0!
0%
0'

#2985000
1!

#2990000
0!
0$
1%
1'

#2995000
1!
0&

#3000000
0!
1$

#3005000
1!
1&

#3010000
0!

#3015000
1!

#3020000
0!

#3025000
1!

#3030000
0!
0%
0'

#3035000
1!

#3040000
0!
0$

#3045000
1!

#3050000
0!
1$

#3055000
1!

#3060000
0!

#3065000
1!

#3070000
0!
1%
1'

#3075000
1!

#3080000
0!
0$
0%
0'

#3085000
1!

#3090000
0!
1$
1%
1'

#3095000
1!

#3100000
0!
0$

#3105000
1!
0&

#3110000
0!
1$

#3115000
1!
1&

#3120000
0!

#3125000
1!

#3130000
0!
0%
0'

#3135000
1!

#3140000
0!

#3145000
1!

#3150000
0!

#3155000
1!

#3160000
0!

#3165000
1!

#3170000
0!
1%
1'

#3175000
1!

#3180000
0!

#3185000
1!

#3190000
0!
0%
0'

#3195000
1!

#3200000
0!
0$
1%
1'

#3205000
1!
0&

#3210000
0!
1$
0'

#3215000
1!
0%
1&

#3220000
0!
1%
1'

#3225000
1!

#3230000
0!

#3235000
1!

#3240000
0!
0%
0'

#3245000
1!

#3250000
0!
1%
1'

#3255000
1!

#3260000
0!
0%
0'

#3265000
1!

#3270000
0!
1%
1'

#3275000
1!

#3280000
0!

#3285000
1!

#3290000
0!
0%
0'

#3295000
1!

#3300000
0!
1%
1'

#3305000
1!

#3310000
0!

#3315000
1!

#3320000
0!

#3325000
1!

#3330000
0!
0$
0%
0'

#3335000
1!

#3340000
0!
1%
1'

#3345000
1!
0&

#3350000
0!
1$

#3355000
1!
1&

#3360000
0!
0$
0%
0'

#3365000
1!

#3370000
0!

#3375000
1!

#3380000
0!
1%
1'

#3385000
1!
0&

#3390000
0!
1$
0'

#3395000
1!
0%
1&

#3400000
0!
0$
1%
1'

#3405000
1!
0&

#3410000
0!
1$

#3415000
1!
1&

#3420000
0!
0$
0%
0'

#3425000
1!

#3430000
0!

#3435000
1!

#3440000
0!
1$
1%
1'

#3445000
1!

#3450000
0!

#3455000
1!

#3460000
0!

#3465000
1!

#3470000
0!

#3475000
1!

#3480000
0!

#3485000
1!

#3490000
0!
0%
0'

#3495000
1!

#3500000
0!

